langchain_recallio/__init__.py
langchain_recallio/memory.py
tests/__init__.py
tests/test_memory.py
langchain_recallio-1.1.0.dist-info/METADATA
langchain_recallio-1.1.0.dist-info/WHEEL
langchain_recallio-1.1.0.dist-info/top_level.txt
langchain_recallio-1.1.0.dist-info/RECORD
