Metadata-Version: 2.4
Name: langchain-recallio
Version: 1.1.0
Summary: Drop-in RecallIO Memory for LangChain
Author: RecallIO
Author-email: Recallio Team <support@recallio.com>
Project-URL: Homepage, https://recallio.ai
Requires-Python: >=3.8
Requires-Dist: requests>=2.31
Dynamic: author
Dynamic: requires-python
